README.md
setup.py
ccwt_client/__init__.py
ccwt_client/ccwt_feed.py
ccwt_client/core.py
ccwt_client/logger.py
ccwt_client.egg-info/PKG-INFO
ccwt_client.egg-info/SOURCES.txt
ccwt_client.egg-info/dependency_links.txt
ccwt_client.egg-info/requires.txt
ccwt_client.egg-info/top_level.txt
test/test_client.py