Metadata-Version: 2.1
Name: ccwt-client
Version: 0.8
Summary: ccwt server client
Home-page: https://github.com/nigelliyang/ccwt_client
Author: xycfree
Author-email: xycfree@163.com
License: Apache v2.0 License
Platform: UNKNOWN
Classifier: License :: OSI Approved :: Apache Software License
Classifier: Development Status :: 5 - Production/Stable
Classifier: Intended Audience :: Developers
Classifier: Programming Language :: Python
Classifier: Programming Language :: Python :: 2.7
Classifier: Programming Language :: Python :: 3.6
Classifier: Topic :: Software Development :: Libraries :: Python Modules
